Metadata-Version: 2.1
Name: kbert
Version: 0.1.2
Summary: TensorFlow2.0 with Keras For BERT
Home-page: https://github.com/sunyanhust/kbert
Author: SunYan
Author-email: sunyanhust@163.com
License: MIT License
Platform: UNKNOWN
Classifier: License :: OSI Approved :: Apache Software License
Classifier: Programming Language :: Python :: 3.6
Classifier: Programming Language :: Python :: Implementation :: CPython
Classifier: Programming Language :: Python :: Implementation :: PyPy
Requires-Python: >3.6
Requires-Dist: sentencepiece
Requires-Dist: tensorflow (==2.1.0)
Requires-Dist: numpy (==1.16.4)
Requires-Dist: tqdm
